Workbook

Sheet Cover
B2: TESCO PLC
B5: 3-Statement Integrated Financial Model
B7: FY2020–FY2024 Historical | FY2025E–FY2027E Projection
B10: Prepared by: | C10: Alugu Rohit Raj
B11: Qualification: | C11: MSc Accounting and Finance, Part Qualified ACCA
B12: Date: | C12: June 2025
B13: Currency: | C13: GBP £ Millions
B14: Fiscal Year End: | C14: February (Tesco FY convention)
B15: Data Source: | C15: Tesco PLC Annual Reports 2020–2024 | StockAnalysis.com | Yahoo Finance
B17: WORKSHEET GUIDE
B18: Assumptions | C18: Forward-looking drivers & key model inputs
B19: Historical Data | C19: 5-year raw financials (FY2020–FY2024)
B20: Income Statement | C20: Historical + 3-year projected P&L
B21: Balance Sheet | C21: Historical + 3-year projected BS
B22: Cash Flow | C22: Historical + 3-year projected CFS
B23: Dashboard | C23: KPI charts & key ratio summary
B24: Model Checks | C24: Balance check & integrity tests

Sheet Assumptions
A1: ASSUMPTIONS & KEY DRIVERS
A2: All projections use 3-year averages of historical data as base assumptions
A3: Driver | B3: FY2025E | C3: FY2026E | D3: FY2027E
A4: INCOME STATEMENT ASSUMPTIONS
A5: Revenue Growth Rate | B5: 0.026 | C5: 0.02 | D5: 0.02
A6: Gross Margin % | B6: 0.071 | C6: 0.071 | D6: 0.072
A7: SG&A as % of Revenue | B7: 0.03 | C7: 0.03 | D7: 0.03
A8: EBITDA Margin % | B8: 0.066 | C8: 0.066 | D8: 0.067
A9: D&A as % of Revenue | B9: 0.026 | C9: 0.026 | D9: 0.026
A10: Interest Income (£m) | B10: 270 | C10: 265 | D10: 260
A11: Interest Expense (£m) | B11: 790 | C11: 780 | D11: 770
A12: Effective Tax Rate | B12: 0.255 | C12: 0.255 | D12: 0.255
A14: WORKING CAPITAL ASSUMPTIONS
A15: Inventory Days (DIO) | B15: 14 | C15: 14 | D15: 14
A16: Debtor Days (DSO) | B16: 5 | C16: 5 | D16: 5
A17: Creditor Days (DPO) | B17: 38 | C17: 38 | D17: 38
A19: CAPITAL EXPENDITURE & BALANCE SHEET
A20: Capex as % of Revenue | B20: 0.021 | C20: 0.021 | D20: 0.021
A21: D&A (£m) | B21: 1720 | C21: 1750 | D21: 1780
A22: Net Debt Target (£m) | B22: 9500 | C22: 9200 | D22: 8900
A25: KEY ASSUMPTIONS RATIONALE
A26: • Revenue Growth: Based on 3-yr CAGR (FY22-FY24 = +5.5%), conservative 2.0–2.6% used for projections
A27: • Gross Margin: 5-yr average ~7.1%; FY2023 was anomaly (supply chain costs) – normalised to 7.1-7.2%
A28: • SG&A: Stable at ~3.0% of revenue; Tesco Save-to-Invest programme has kept opex flat
A29: • Interest Expense: Slight reduction assumed as Tesco Bank sale reduces leverage
A30: • Tax Rate: 25.5% reflects UK corporation tax increase from April 2023
A31: • Capex: 2.1% of revenue consistent with maintenance + selective store investment

Sheet Historical Data
A1: TESCO PLC — HISTORICAL FINANCIAL DATA (FY2020–FY2024)
A2: Source: Tesco PLC Annual Reports 2020–2024 | StockAnalysis.com | Yahoo Finance. All figures in £ Millions.
B3: FY2020 | C3: FY2021 | D3: FY2022 | E3: FY2023 | F3: FY2024
A4: INCOME STATEMENT (£m)
A5: Revenue | B5: 58091 | C5: 53440 | D5: 61344 | E5: 65322 | F5: 68187
A6: Cost of Revenue | B6: 53640 | C6: 49384 | D6: 56750 | E6: 61961 | F6: 63338
A7: Gross Profit | B7: 4451 | C7: 4056 | D7: 4594 | E7: 3361 | F7: 4849
A8: SG&A Expenses | B8: 2285 | C8: 2063 | D8: 2073 | E8: 1951 | F8: 2028
A9: EBITDA | B9: 4278 | C9: 4050 | D9: 4278 | E9: 3110 | F9: 4544
A10: Operating Income (EBIT) | B10: 2166 | C10: 1993 | D10: 2560 | E10: 1410 | F10: 2821
A11: Interest Income | B11: 76 | C11: 48 | D11: 9 | E11: 87 | F11: 267
A12: Interest Expense | B12: 574 | C12: 517 | D12: 551 | E12: 623 | F12: 805
A13: Profit Before Tax | B13: 1668 | C13: 1524 | D13: 2033 | E13: 882 | F13: 2289
A14: Income Tax | B14: 458 | C14: 359 | D14: 510 | E14: 224 | F14: 525
A15: Net Income (Continuing Ops) | B15: 1210 | C15: 1165 | D15: 1481 | E15: 737 | F15: 1188
A17: KEY MARGINS
A18: Gross Margin % | B18: 0.076621163 | C18: 0.075898204 | D18: 0.07488915 | E18: 0.051452803 | F18: 0.071113262
A19: EBITDA Margin % | B19: 0.073643077 | C19: 0.075785928 | D19: 0.069737872 | E19: 0.0476103 | F19: 0.066640269
A20: Operating Margin % | B20: 0.037286327 | C20: 0.037294162 | D20: 0.041731873 | E20: 0.021585377 | F20: 0.041371522
A21: Net Profit Margin % | B21: 0.020829388 | C21: 0.02180015 | D21: 0.02414254 | E21: 0.011282569 | F21: 0.017422676
A23: BALANCE SHEET (£m)
A24: — ASSETS —
A25: Cash & Cash Equivalents | B25: 2169 | C25: 1978 | D25: 1771 | E25: 1565 | F25: 1528
A26: Inventories | B26: 2177 | C26: 1970 | D26: 2073 | E26: 2275 | F26: 2348
A27: Trade Receivables | B27: 813 | C27: 801 | D27: 902 | E27: 909 | F27: 919
A28: Other Current Assets | B28: 1050 | C28: 920 | D28: 884 | E28: 974 | F28: 1012
A29: Total Current Assets | B29: 6209 | C29: 5669 | D29: 5630 | E29: 5723 | F29: 5807
A30: Property, Plant & Equipment | B30: 10002 | C30: 9826 | D30: 10093 | E30: 9830 | F30: 9681
A31: Intangible Assets | B31: 2789 | C31: 2658 | D31: 2665 | E31: 2558 | F31: 2568
A32: Right-of-Use Assets (IFRS 16) | B32: 10421 | C32: 10126 | D32: 9986 | E32: 9897 | F32: 9831
A33: Other Non-Current Assets | B33: 15091 | C33: 17233 | D33: 20977 | E33: 17860 | F33: 19152
A34: TOTAL ASSETS | B34: 53102 | C34: 45512 | D34: 49351 | E34: 45868 | F34: 47039
A35: — LIABILITIES —
A36: Trade Payables | B36: 5675 | C36: 5379 | D36: 6032 | E36: 6540 | F36: 6658
A37: Short-term Borrowings | B37: 986 | C37: 1184 | D37: 758 | E37: 773 | F37: 881
A38: Other Current Liabilities | B38: 4882 | C38: 4506 | D38: 4848 | E38: 4571 | F38: 4734
A39: Total Current Liabilities | B39: 11543 | C39: 11069 | D39: 11638 | E39: 11884 | F39: 12273
A40: Long-term Borrowings | B40: 11238 | C40: 9856 | D40: 10869 | E40: 9963 | F40: 9591
A41: Lease Liabilities (IFRS 16) | B41: 10682 | C41: 10126 | D41: 9986 | E41: 9897 | F41: 9831
A42: Other Non-Current Liabilities | B42: 3120 | C42: 2822 | D42: 1869 | E42: 2099 | F42: 3679
A43: TOTAL LIABILITIES | B43: 36583 | C43: 33873 | D43: 33505 | E43: 33643 | F43: 35374
A44: TOTAL EQUITY | B44: 16519 | C44: 11639 | D44: 15846 | E44: 12225 | F44: 11665
A46: CASH FLOW STATEMENT (£m)
A47: Cash from Operating Activities | B47: 2545 | C47: 602 | D47: 3757 | E47: 3722 | F47: 3839
A48: Capital Expenditure (Capex) | B48: -1247 | C48: -1377 | D48: -1178 | E48: -1250 | F48: -1386
A49: Cash from Investing Activities | B49: 2058 | C49: 6171 | D49: -1735 | E49: -706 | F49: -1700
A50: Cash from Financing Activities | B50: -3601 | C50: -7841 | D50: -2234 | E50: -3188 | F50: -1859
A51: Net Change in Cash | B51: 1002 | C51: -1068 | D51: -212 | E51: -172 | F51: 37
A52: Ending Cash Position | B52: 2169 | C52: 1978 | D52: 1771 | E52: 1565 | F52: 1528
A53: Free Cash Flow | B53: 1298 | C53: -775 | D53: 2808 | E53: 2751 | F53: 2731
A54: Note: Free Cash Flow figures represent Tesco's Retail Free Cash Flow (APM) as reported in Annual Reports, which excludes Tesco Bank and includes working capital movements not captured in the simplified Operating CF line above.

Sheet Income Statement
A1: TESCO PLC — CONSOLIDATED INCOME STATEMENT (£m)
A2: Historical: Tesco Annual Reports | Projections: Model-driven from Assumptions sheet
B3: FY2020 | C3: FY2021 | D3: FY2022 | E3: FY2023 | F3: FY2024 | G3: FY2025E | H3: FY2026E | I3: FY2027E
A4: Historical ◄ | F4: ► Projected
A5: Revenue | B5: 58091 | C5: 53440 | D5: 61344 | E5: 65322 | F5: 68187 | G5: =68187*(1+Assumptions!B5) -> 69959.862 | H5: =G5*(1+Assumptions!C5) -> 71359.059 | I5: =H5*(1+Assumptions!D5) -> 72786.24
A6: Cost of Revenue | B6: 53640 | C6: 49384 | D6: 56750 | E6: 61961 | F6: 63338 | G6: =G5*(1-Assumptions!B6) -> 64992.712 | H6: =H5*(1-Assumptions!C6) -> 66292.566 | I6: =I5*(1-Assumptions!D6) -> 67545.631
A7: Gross Profit | B7: 4451 | C7: 4056 | D7: 4594 | E7: 3361 | F7: 4849 | G7: =G5-G6 -> 4967.1502 | H7: =H5-H6 -> 5066.4932 | I7: =I5-I6 -> 5240.6093
A8: Gross Margin % | B8: 0.076621163 | C8: 0.075898204 | D8: 0.07488915 | E8: 0.051452803 | F8: 0.071113262 | G8: =G7/G5 -> 0.071 | H8: =H7/H5 -> 0.071 | I8: =I7/I5 -> 0.072
A9: SG&A Expenses | B9: 2285 | C9: 2063 | D9: 2073 | E9: 1951 | F9: 2028 | G9: =G5*Assumptions!B7 -> 2098.7959 | H9: =H5*Assumptions!C7 -> 2140.7718 | I9: =I5*Assumptions!D7 -> 2183.5872
A10: EBITDA | B10: 4278 | C10: 4050 | D10: 4278 | E10: 3110 | F10: 4544 | G10: =G5*Assumptions!B8 -> 4617.3509 | H10: =H5*Assumptions!C8 -> 4709.6979 | I10: =I5*Assumptions!D8 -> 4876.6781
A11: EBITDA Margin % | B11: 0.073643077 | C11: 0.075785928 | D11: 0.069737872 | E11: 0.0476103 | F11: 0.066640269 | G11: =G10/G5 -> 0.066 | H11: =H10/H5 -> 0.066 | I11: =I10/I5 -> 0.067
A12: Depreciation & Amortisation | B12: 2112 | C12: 2057 | D12: 1718 | E12: 1700 | F12: 1723 | G12: =Assumptions!B21 -> 1720 | H12: =Assumptions!C21 -> 1750 | I12: =Assumptions!D21 -> 1780
A13: Operating Income (EBIT) | B13: 2166 | C13: 1993 | D13: 2560 | E13: 1410 | F13: 2821 | G13: =G10-G12 -> 2897.3509 | H13: =H10-H12 -> 2959.6979 | I13: =I10-I12 -> 3096.6781
A14: Operating Margin % | B14: 0.037286327 | C14: 0.037294162 | D14: 0.041731873 | E14: 0.021585377 | F14: 0.041371522 | G14: =G13/G5 -> 0.041414474 | H14: =H13/H5 -> 0.041476134 | I14: =I13/I5 -> 0.042544828
A15: Interest Income | B15: 76 | C15: 48 | D15: 9 | E15: 87 | F15: 267 | G15: =Assumptions!B10 -> 270 | H15: =Assumptions!C10 -> 265 | I15: =Assumptions!D10 -> 260
A16: Interest Expense | B16: 574 | C16: 517 | D16: 551 | E16: 623 | F16: 805 | G16: =Assumptions!B11 -> 790 | H16: =Assumptions!C11 -> 780 | I16: =Assumptions!D11 -> 770
A17: Profit Before Tax | B17: 1668 | C17: 1524 | D17: 2033 | E17: 882 | F17: 2289 | G17: =G13+G15-G16 -> 2377.3509 | H17: =H13+H15-H16 -> 2444.6979 | I17: =I13+I15-I16 -> 2586.6781
A18: Income Tax | B18: 458 | C18: 359 | D18: 510 | E18: 224 | F18: 525 | G18: =G17*Assumptions!B12 -> 606.22448 | H18: =H17*Assumptions!C12 -> 623.39797 | I18: =I17*Assumptions!D12 -> 659.60292
A19: NET INCOME | B19: 1210 | C19: 1165 | D19: 1481 | E19: 737 | F19: 1188 | G19: =G17-G18 -> 1771.1264 | H19: =H17-H18 -> 1821.2999 | I19: =I17-I18 -> 1927.0752
A20: Net Profit Margin % | B20: 0.020829388 | C20: 0.02180015 | D20: 0.02414254 | E20: 0.011282569 | F20: 0.017422676 | G20: =G19/G5 -> 0.025316322 | H20: =H19/H5 -> 0.025523037 | I20: =I19/I5 -> 0.026475817
A21: Note: FY2025E revenue seed value = FY2024 actual (£68,187m). All projections driven by Assumptions sheet.
A22: Note on Net Income: FY2024 statutory net income of £1,188m was suppressed by one-off adjusting items (restructuring, property write-downs, bank discontinuation). Projected NI uses normalised margins; the increase to £1,771m in FY2025E reflects removal of these one-off charges.

Sheet Balance Sheet
A1: TESCO PLC — CONSOLIDATED BALANCE SHEET (£m)
A2: Historical: Tesco Annual Reports | Projections driven by working capital days & revenue assumptions
B3: FY2020 | C3: FY2021 | D3: FY2022 | E3: FY2023 | F3: FY2024 | G3: FY2025E | H3: FY2026E | I3: FY2027E
A4: ASSETS
A5: Cash & Cash Equivalents | B5: 2169 | C5: 1978 | D5: 1771 | E5: 1565 | F5: 1528 | G5: =1528*(1.01) -> 1543.28 | H5: =1528*(1.02) -> 1558.56 | I5: =1528*(1.03) -> 1573.84
A6: Inventories | B6: 2177 | C6: 1970 | D6: 2073 | E6: 2275 | F6: 2348 | G6: ='Income Statement'!G6*Assumptions!B15/365 -> 2492.8711 | H6: ='Income Statement'!H6*Assumptions!C15/365 -> 2542.7286 | I6: ='Income Statement'!I6*Assumptions!D15/365 -> 2590.7913
A7: Trade Receivables | B7: 813 | C7: 801 | D7: 902 | E7: 909 | F7: 919 | G7: ='Income Statement'!G5*Assumptions!B16/365 -> 958.35427 | H7: ='Income Statement'!H5*Assumptions!C16/365 -> 977.52136 | I7: ='Income Statement'!I5*Assumptions!D16/365 -> 997.07179
A8: Other Current Assets | B8: 1050 | C8: 920 | D8: 884 | E8: 974 | F8: 1012 | G8: =1012 -> 1012 | H8: =1012 -> 1012 | I8: =1012 -> 1012
A9: Total Current Assets | B9: 6209 | C9: 5669 | D9: 5630 | E9: 5723 | F9: 5807 | G9: =G5+G6+G7+G8 -> 6006.5054 | H9: =H5+H6+H7+H8 -> 6090.8099 | I9: =I5+I6+I7+I8 -> 6173.7031
A10: Property, Plant & Equipment | B10: 10002 | C10: 9826 | D10: 10093 | E10: 9830 | F10: 9681 | G10: =9681-300 -> 9381 | H10: =9381-300 -> 9081 | I10: =9081-300 -> 8781
A11: Intangible Assets | B11: 2789 | C11: 2658 | D11: 2665 | E11: 2558 | F11: 2568 | G11: =2568 -> 2568 | H11: =2568 -> 2568 | I11: =2568 -> 2568
A12: Right-of-Use Assets (IFRS 16) | B12: 10421 | C12: 10126 | D12: 9986 | E12: 9897 | F12: 9831 | G12: =9831-50 -> 9781 | H12: =9781-50 -> 9731 | I12: =9731-50 -> 9681
A13: Other Non-Current Assets | B13: 15091 | C13: 17233 | D13: 20977 | E13: 17860 | F13: 19152 | G13: =19152 -> 19152 | H13: =19152 -> 19152 | I13: =19152 -> 19152
A14: TOTAL ASSETS | B14: 53102 | C14: 45512 | D14: 49351 | E14: 45868 | F14: 47039 | G14: =G9+G10+G11+G12+G13 -> 46888.505 | H14: =H9+H10+H11+H12+H13 -> 46622.81 | I14: =I9+I10+I11+I12+I13 -> 46355.703
A16: LIABILITIES
A17: Trade Payables | B17: 5675 | C17: 5379 | D17: 6032 | E17: 6540 | F17: 6658 | G17: ='Income Statement'!G6*Assumptions!B17/365 -> 6766.3645 | H17: ='Income Statement'!H6*Assumptions!C17/365 -> 6901.6918 | I17: ='Income Statement'!I6*Assumptions!D17/365 -> 7032.1479
A18: Short-term Borrowings | B18: 986 | C18: 1184 | D18: 758 | E18: 773 | F18: 881 | G18: =881 -> 881 | H18: =881 -> 881 | I18: =881 -> 881
A19: Other Current Liabilities | B19: 4882 | C19: 4506 | D19: 4848 | E19: 4571 | F19: 4734 | G19: =4734 -> 4734 | H19: =4734 -> 4734 | I19: =4734 -> 4734
A20: Total Current Liabilities | B20: 11543 | C20: 11069 | D20: 11638 | E20: 11884 | F20: 12273 | G20: =G17+G18+G19 -> 12381.365 | H20: =H17+H18+H19 -> 12516.692 | I20: =I17+I18+I19 -> 12647.148
A21: Long-term Borrowings | B21: 11238 | C21: 9856 | D21: 10869 | E21: 9963 | F21: 9591 | G21: =9200 -> 9200 | H21: =8900 -> 8900 | I21: =8600 -> 8600
A22: Lease Liabilities (IFRS 16) | B22: 10682 | C22: 10126 | D22: 9986 | E22: 9897 | F22: 9831 | G22: =9781 -> 9781 | H22: =9731 -> 9731 | I22: =9681 -> 9681
A23: Other Non-Current Liabilities | B23: 3120 | C23: 2822 | D23: 1869 | E23: 2099 | F23: 3679 | G23: =3679 -> 3679 | H23: =3679 -> 3679 | I23: =3679 -> 3679
A24: TOTAL LIABILITIES | B24: 36583 | C24: 33873 | D24: 33505 | E24: 33643 | F24: 35374 | G24: =G20+G21+G22+G23 -> 35041.365 | H24: =H20+H21+H22+H23 -> 34826.692 | I24: =I20+I21+I22+I23 -> 34607.148
A26: EQUITY
A27: TOTAL EQUITY | B27: 16519 | C27: 11639 | D27: 15848 | E27: 12225 | F27: 11665 | G27: =G14-G24 -> 11847.141 | H27: =H14-H24 -> 11796.118 | I27: =I14-I24 -> 11748.555
A29: BALANCE CHECK (Assets = Liabilities + Equity)
A30: Total Liabilities + Equity | B30: 53102 | C30: 45512 | D30: 49353 | E30: 45868 | F30: 47039 | G30: =G24+G27 -> 46888.505 | H30: =H24+H27 -> 46622.81 | I30: =I24+I27 -> 46355.703
A31: Total Assets | B31: 53102 | C31: 45512 | D31: 49351 | E31: 45868 | F31: 47039 | G31: =G14 -> 46888.505 | H31: =H14 -> 46622.81 | I31: =I14 -> 46355.703
A32: DIFFERENCE (Must be ZERO) | B32: 0 | C32: 0 | D32: 0 | E32: 0 | F32: 0 | G32: =G30-G31 -> 0 | H32: =H30-H31 -> 0 | I32: =I30-I31 -> 0

Sheet Cash Flow
A1: TESCO PLC — CONSOLIDATED CASH FLOW STATEMENT (£m)
A2: Historical: Yahoo Finance / Tesco Annual Reports | Projections: Derived from IS and BS
B3: FY2020 | C3: FY2021 | D3: FY2022 | E3: FY2023 | F3: FY2024 | G3: FY2025E | H3: FY2026E | I3: FY2027E
A4: OPERATING ACTIVITIES
A5: Net Income | B5: 1210 | C5: 1165 | D5: 1481 | E5: 737 | F5: 1188 | G5: ='Income Statement'!G19 -> 1771.1264 | H5: ='Income Statement'!H19 -> 1821.2999 | I5: ='Income Statement'!I19 -> 1927.0752
A6: Add: Depreciation & Amortisation | B6: 2112 | C6: 2057 | D6: 1718 | E6: 1700 | F6: 1723 | G6: ='Income Statement'!G12 -> 1720 | H6: ='Income Statement'!H12 -> 1750 | I6: ='Income Statement'!I12 -> 1780
A7: Changes in Working Capital | B7: -50 | C7: -120 | D7: 100 | E7: -200 | F7: -120 | G7: =-50 -> -50 | H7: =-50 -> -50 | I7: =-50 -> -50
A8: Tax Paid & Other Operating Items | B8: -530 | C8: -365 | D8: -690 | E8: -680 | F8: -760 | G8: =-600 -> -600 | H8: =-620 -> -620 | I8: =-640 -> -640
A9: NET CASH FROM OPERATING ACTIVITIES | B9: 2545 | C9: 602 | D9: 3757 | E9: 3722 | F9: 3839 | G9: =G5+G6+G7+G8 -> 2841.1264 | H9: =H5+H6+H7+H8 -> 2901.2999 | I9: =I5+I6+I7+I8 -> 3017.0752
A11: INVESTING ACTIVITIES
A12: Capital Expenditure (Capex) | B12: -1247 | C12: -1377 | D12: -1178 | E12: -1250 | F12: -1386 | G12: =-('Income Statement'!G5*Assumptions!B20) -> -1469.1571 | H12: =-('Income Statement'!H5*Assumptions!C20) -> -1498.5402 | I12: =-('Income Statement'!I5*Assumptions!D20) -> -1528.511
A13: Proceeds from Asset Sales / Other | B13: 2305 | C13: 7548 | D13: -557 | E13: 529 | F13: -314 | G13: =0 -> 0 | H13: =0 -> 0 | I13: =0 -> 0
A14: NET CASH FROM INVESTING ACTIVITIES | B14: 2058 | C14: 6171 | D14: -1735 | E14: -706 | F14: -1700 | G14: =G12+G13 -> -1469.1571 | H14: =H12+H13 -> -1498.5402 | I14: =I12+I13 -> -1528.511
A16: FINANCING ACTIVITIES
A17: Dividends Paid | B17: -549 | C17: -472 | D17: -750 | E17: -821 | F17: -883 | G17: =-900 -> -900 | H17: =-920 -> -920 | I17: =-940 -> -940
A18: Share Buybacks | B18: -66 | C18: 0 | D18: -422 | E18: -867 | F18: -845 | G18: =-500 -> -500 | H18: =-400 -> -400 | I18: =-300 -> -300
A19: Net Debt Change / Other Financing | B19: -2986 | C19: -7369 | D19: -2062 | E19: -1500 | F19: -131 | G19: =-300 -> -300 | H19: =-200 -> -200 | I19: =-200 -> -200
A20: NET CASH FROM FINANCING ACTIVITIES | B20: -3601 | C20: -7841 | D20: -2234 | E20: -3188 | F20: -1859 | G20: =G17+G18+G19 -> -1700 | H20: =H17+H18+H19 -> -1520 | I20: =I17+I18+I19 -> -1440
A22: CASH SUMMARY
A23: Net Change in Cash | B23: 1002 | C23: -1068 | D23: -212 | E23: -172 | F23: 37 | G23: =G9+G14+G20 -> -328.03069 | H23: =H9+H14+H20 -> -117.2403 | I23: =I9+I14+I20 -> 48.564142
A24: Opening Cash Balance | C24: 2169 | D24: 1978 | E24: 1771 | F24: 1565 | G24: =1528 -> 1528 | H24: =1543 -> 1543 | I24: =1558 -> 1558
A25: ENDING CASH BALANCE | B25: 2169 | C25: 1978 | D25: 1771 | E25: 1565 | F25: 1528 | G25: =G24+G23 -> 1199.9693 | H25: =H24+H23 -> 1425.7597 | I25: =I24+I23 -> 1606.5641
A26: FREE CASH FLOW (Operating – Capex) | B26: 1298 | C26: -775 | D26: 2808 | E26: 2751 | F26: 2731 | G26: =G9+G12 -> 1371.9693 | H26: =H9+H12 -> 1402.7597 | I26: =I9+I12 -> 1488.5641

Sheet Dashboard
A1: TESCO PLC — FINANCIAL PERFORMANCE DASHBOARD
A2: All figures £m | Historical FY2020–FY2024 | Projected FY2025E–FY2027E
B3: FY2024 Revenue | D3: FY2024 EBITDA | F3: FY2024 Net Income | H3: FY2024 FCF
B4: £68,187m | D4: £4,544m | F4: £1,188m | H4: £2,731m
B5: +4.4% YoY | D5: 6.7% margin | F5: 1.7% margin (cont. ops) | H5: 4.0% FCF yield
A7: DATA TABLE — FOR CHART REFERENCE (£m)
B8: FY2020 | C8: FY2021 | D8: FY2022 | E8: FY2023 | F8: FY2024 | G8: FY2025E | H8: FY2026E | I8: FY2027E
A9: Revenue (£m) | B9: 58091 | C9: 53440 | D9: 61344 | E9: 65322 | F9: 68187 | G9: ='Income Statement'!G5 -> 69959.862 | H9: ='Income Statement'!H5 -> 71359.059 | I9: ='Income Statement'!I5 -> 72786.24
A10: Gross Profit (£m) | B10: 4451 | C10: 4056 | D10: 4594 | E10: 3361 | F10: 4849 | G10: ='Income Statement'!G7 -> 4967.1502 | H10: ='Income Statement'!H7 -> 5066.4932 | I10: ='Income Statement'!I7 -> 5240.6093
A11: EBITDA (£m) | B11: 4278 | C11: 4050 | D11: 4278 | E11: 3110 | F11: 4544 | G11: ='Income Statement'!G10 -> 4617.3509 | H11: ='Income Statement'!H10 -> 4709.6979 | I11: ='Income Statement'!I10 -> 4876.6781
A12: Net Income (£m) | B12: 1210 | C12: 1165 | D12: 1481 | E12: 737 | F12: 1188 | G12: ='Income Statement'!G19 -> 1771.1264 | H12: ='Income Statement'!H19 -> 1821.2999 | I12: ='Income Statement'!I19 -> 1927.0752
A13: Free Cash Flow (£m) | B13: 1298 | C13: -775 | D13: 2808 | E13: 2751 | F13: 2731 | G13: ='Cash Flow'!G26 -> 1371.9693 | H13: ='Cash Flow'!H26 -> 1402.7597 | I13: ='Cash Flow'!I26 -> 1488.5641
A14: Gross Margin % | B14: 0.076621163 | C14: 0.075898204 | D14: 0.07488915 | E14: 0.051452803 | F14: 0.071113262 | G14: ='Income Statement'!G7/'Income Statement'!G5 -> 0.071 | H14: ='Income Statement'!H7/'Income Statement'!H5 -> 0.071 | I14: ='Income Statement'!I7/'Income Statement'!I5 -> 0.072
A15: EBITDA Margin % | B15: 0.073643077 | C15: 0.075785928 | D15: 0.069737872 | E15: 0.0476103 | F15: 0.066640269 | G15: ='Income Statement'!G10/'Income Statement'!G5 -> 0.066 | H15: ='Income Statement'!H10/'Income Statement'!H5 -> 0.066 | I15: ='Income Statement'!I10/'Income Statement'!I5 -> 0.067
A16: Net Margin % | B16: 0.020829388 | C16: 0.02180015 | D16: 0.02414254 | E16: 0.011282569 | F16: 0.017422676 | G16: ='Income Statement'!G19/'Income Statement'!G5 -> 0.025316322 | H16: ='Income Statement'!H19/'Income Statement'!H5 -> 0.025523037 | I16: ='Income Statement'!I19/'Income Statement'!I5 -> 0.026475817
A18: KEY FINANCIAL RATIOS
B19: FY2020 | C19: FY2021 | D19: FY2022 | E19: FY2023 | F19: FY2024 | G19: FY2025E | H19: FY2026E | I19: FY2027E
A20: Return on Equity (ROE) | B20: 0.073248986 | C20: 0.10009451 | D20: 0.093450278 | E20: 0.060286299 | F20: 0.10184312 | G20: ='Income Statement'!G19/'Balance Sheet'!G27 -> 0.14949821 | H20: ='Income Statement'!H19/'Balance Sheet'!H27 -> 0.15439825 | I20: ='Income Statement'!I19/'Balance Sheet'!I27 -> 0.16402657
A21: Current Ratio (x) | B21: 0.54 | C21: 0.51 | D21: 0.48 | E21: 0.48 | F21: 0.47 | G21: ='Balance Sheet'!G9/'Balance Sheet'!G20 -> 0.48512467 | H21: ='Balance Sheet'!H9/'Balance Sheet'!H20 -> 0.48661499 | I21: ='Balance Sheet'!I9/'Balance Sheet'!I20 -> 0.48814983
A22: Net Debt / EBITDA (x) | B22: 2.4 | C22: 2.2 | D22: 2.3 | E22: 2.9 | F22: 2 | G22: =('Balance Sheet'!G21+'Balance Sheet'!G18-'Balance Sheet'!G5)/'Income Statement'!G10 -> 1.8490516 | H22: =('Balance Sheet'!H21+'Balance Sheet'!H18-'Balance Sheet'!H5)/'Income Statement'!H10 -> 1.745853 | I22: =('Balance Sheet'!I21+'Balance Sheet'!I18-'Balance Sheet'!I5)/'Income Statement'!I10 -> 1.6214234
A23: Interest Coverage (x) | B23: 3.8 | C23: 3.9 | D23: 4.6 | E23: 2.3 | F23: 3.5 | G23: ='Income Statement'!G13/'Income Statement'!G16 -> 3.6675328 | H23: ='Income Statement'!H13/'Income Statement'!H16 -> 3.7944845 | I23: ='Income Statement'!I13/'Income Statement'!I16 -> 4.0216599

Sheet Model Checks
A1: MODEL INTEGRITY CHECKS
A2: All checks below should show PASS (green). Any FAIL requires investigation.
A4: CHECK DESCRIPTION | B4: VALUE | C4: STATUS
A5: FY2024 Revenue matches Annual Report (£68,187m) | B5: ='Income Statement'!F5 -> 68187 | C5: =IF(ABS(B5-68187)<1,"✓ PASS","✗ FAIL") -> ✓ PASS
A6: FY2024 Net Income matches Annual Report (£1,188m) | B6: ='Income Statement'!F19 -> 1188 | C6: =IF(ABS(B6-1188)<1,"✓ PASS","✗ FAIL") -> ✓ PASS
A7: FY2024 Total Assets matches Annual Report (£47,039m) | B7: ='Balance Sheet'!F14 -> 47039 | C7: =IF(ABS(B7-47039)<1,"✓ PASS","✗ FAIL") -> ✓ PASS
A8: FY2024 Total Equity matches Annual Report (£11,665m) | B8: ='Balance Sheet'!F27 -> 11665 | C8: =IF(ABS(B8-11665)<1,"✓ PASS","✗ FAIL") -> ✓ PASS
A9: FY2024 Operating Cash Flow matches (£3,839m) | B9: ='Cash Flow'!F9 -> 3839 | C9: =IF(ABS(B9-3839)<1,"✓ PASS","✗ FAIL") -> ✓ PASS
A10: Income Statement: FY2025E Revenue is positive | B10: ='Income Statement'!G5 -> 69959.862 | C10: =IF(B10>0,"✓ PASS","✗ FAIL") -> ✓ PASS
A11: Income Statement: FY2025E Net Income is positive | B11: ='Income Statement'!G19 -> 1771.1264 | C11: =IF(B11>0,"✓ PASS","✗ FAIL") -> ✓ PASS
A12: Balance Sheet: FY2025E Total Assets = Liabilities + Equity | B12: ='Balance Sheet'!G14-'Balance Sheet'!G24-'Balance Sheet'!G27 -> 0 | C12: =IF(ABS(B12)<1,"✓ PASS","✗ FAIL") -> ✓ PASS
A13: Balance Sheet: FY2026E Total Assets = Liabilities + Equity | B13: ='Balance Sheet'!H14-'Balance Sheet'!H24-'Balance Sheet'!H27 -> 0 | C13: =IF(ABS(B13)<1,"✓ PASS","✗ FAIL") -> ✓ PASS
A14: Cash Flow: FY2025E Operating CF is positive | B14: ='Cash Flow'!G9 -> 2841.1264 | C14: =IF(B14>0,"✓ PASS","✗ FAIL") -> ✓ PASS
A15: Revenue Growth FY2025E vs FY2024 is 2–4% | B15: ='Income Statement'!G5/'Income Statement'!F5-1 -> 0.026 | C15: =IF(AND(B15>=0.01,B15<=0.05),"✓ PASS","✗ FAIL") -> ✓ PASS
A16: EBITDA Margin FY2025E is 5–10% | B16: ='Income Statement'!G10/'Income Statement'!G5 -> 0.066 | C16: =IF(AND(B16>=0.05,B16<=0.1),"✓ PASS","✗ FAIL") -> ✓ PASS
